{
  "$type": "Forguncy.SaveLoad.ServerCommandSaveData, ServerDesignerCommon",
  "Name": "产品维护",
  "Enabled": true,
  "Triggers": {
    "$type": "System.Collections.Generic.List`1[[Forguncy.SaveLoad.TriggerSaveDataBase, ServerDesignerCommon]], System.Private.CoreLib",
    "$values": [
      {
        "$type": "Forguncy.SaveLoad.PostRequestTriggerSaveData, ServerDesignerCommon",
        "Permission": {
          "$type": "Forguncy.SaveLoad.ServerCommandPermissionSaveData, ServerDesignerCommon",
          "PermissionData": {
            "$type": "Forguncy.RbacPermission.Core.Impl.ServerCommand.ServerCommandPermissionData, Forguncy.RbacPermission.Core",
            "permissionResource": {
              "$type": "Forguncy.RbacPermission.Core.Impl.ServerCommand.ServerCommandPermissionResource, Forguncy.RbacPermission.Core"
            },
            "permissionBindings": {
              "$type": "System.Collections.Generic.List`1[[Forguncy.RbacPermission.Core.Impl.ServerCommand.IServerCommandPermissionBinding, Forguncy.RbacPermission.Core]], System.Private.CoreLib",
              "$values": [
                {
                  "$type": "Forguncy.RbacPermission.Core.Impl.ServerCommand.ServerCommandPermissionBinding, Forguncy.RbacPermission.Core",
                  "permissionGroups": {
                    "$type": "System.Collections.Generic.List`1[[System.String, System.Private.CoreLib]], System.Private.CoreLib",
                    "$values": [
                      "e8cd8c16-7795-4e40-9235-454e164dda34"
                    ]
                  }
                }
              ]
            }
          }
        },
        "Parameters": {
          "$type": "System.Collections.Generic.List`1[[Forguncy.SaveLoad.PostRequestParameterSaveData, ServerDesignerCommon]], System.Private.CoreLib",
          "$values": [
            {
              "$type": "Forguncy.SaveLoad.PostRequestParameterSaveData, ServerDesignerCommon",
              "Name": "产品ID",
              "DataValidationInfo": {
                "$type": "Forguncy.SaveLoad.DataValidationInfoSaveData, ServerDesignerCommon"
              }
            },
            {
              "$type": "Forguncy.SaveLoad.PostRequestParameterSaveData, ServerDesignerCommon",
              "Name": "产品编号",
              "DataValidationInfo": {
                "$type": "Forguncy.SaveLoad.DataValidationInfoSaveData, ServerDesignerCommon"
              }
            },
            {
              "$type": "Forguncy.SaveLoad.PostRequestParameterSaveData, ServerDesignerCommon",
              "Name": "名称",
              "DataValidationInfo": {
                "$type": "Forguncy.SaveLoad.DataValidationInfoSaveData, ServerDesignerCommon"
              }
            },
            {
              "$type": "Forguncy.SaveLoad.PostRequestParameterSaveData, ServerDesignerCommon",
              "Name": "类型",
              "DataValidationInfo": {
                "$type": "Forguncy.SaveLoad.DataValidationInfoSaveData, ServerDesignerCommon"
              }
            },
            {
              "$type": "Forguncy.SaveLoad.PostRequestParameterSaveData, ServerDesignerCommon",
              "Name": "定价",
              "DataValidationInfo": {
                "$type": "Forguncy.SaveLoad.DataValidationInfoSaveData, ServerDesignerCommon"
              }
            },
            {
              "$type": "Forguncy.SaveLoad.PostRequestParameterSaveData, ServerDesignerCommon",
              "Name": "备注",
              "DataValidationInfo": {
                "$type": "Forguncy.SaveLoad.DataValidationInfoSaveData, ServerDesignerCommon"
              }
            }
          ]
        }
      }
    ]
  },
  "Commands": {
    "$type": "System.Collections.Generic.List`1[[GrapeCity.Forguncy.Commands.Command, Forguncy.Commands]], System.Private.CoreLib",
    "$values": [
      {
        "$type": "Forguncy.Model.ServerTransactionCommand, ServerDesignerCommon",
        "CommandList": {
          "$type": "System.Collections.Generic.List`1[[GrapeCity.Forguncy.Commands.Command, Forguncy.Commands]], System.Private.CoreLib",
          "$values": [
            {
              "$type": "Forguncy.Model.ConditionCommand, ServerDesignerCommon",
              "ConditionAndCommandPairList": {
                "$type": "System.Collections.Generic.List`1[[Forguncy.Model.ConditionAndCommandPair, ServerDesignerCommon]], System.Private.CoreLib",
                "$values": [
                  {
                    "$type": "Forguncy.Model.ConditionAndCommandPair, ServerDesignerCommon",
                    "Condition": {
                      "$type": "Forguncy.Model.IfCondition, ServerDesignerCommon",
                      "param": {
                        "$type": "Forguncy.Model.IfConditionServerSiteParam, ServerDesignerCommon",
                        "ParamObject": {
                          "$type": "Forguncy.Model.FormulaReferObject, ServerDesignerCommon",
                          "SerializeProperty": "=产品ID"
                        }
                      },
                      "value": "0",
                      "compareType": 2
                    },
                    "CommandList": {
                      "$type": "System.Collections.Generic.List`1[[GrapeCity.Forguncy.Commands.Command, Forguncy.Commands]], System.Private.CoreLib",
                      "$values": [
                        {
                          "$type": "Forguncy.Model.UpdateDataTableCommand, ServerDesignerCommon",
                          "TableName": "产品表",
                          "ShowConfirm": false,
                          "RowsToUpdate": 1,
                          "RowsToUpdateCondition": {
                            "$type": "ForguncyDataAccess.GeneralCESqlCondition, ForguncyDataAccess",
                            "ColumnBindingInfo": {
                              "$type": "ForguncyDataAccess.BindingInfo, ForguncyDataAccess",
                              "TableName": "产品表",
                              "ColumnName": "ID",
                              "GUID": "3d229614-a4d5-428b-9ec2-fa757cafb436"
                            },
                            "Value": {
                              "$type": "Forguncy.Model.FormulaReferObject, ServerDesignerCommon",
                              "SerializeProperty": "=产品ID"
                            }
                          },
                          "UpdateBindingValues": {
                            "$type": "System.Collections.Generic.List`1[[Forguncy.Model.UpdateBindingValueItem, ServerDesignerCommon]], System.Private.CoreLib",
                            "$values": [
                              {
                                "$type": "Forguncy.Model.UpdateBindingValueItem, ServerDesignerCommon",
                                "BindingInfo": {
                                  "$type": "ForguncyDataAccess.BindingInfo, ForguncyDataAccess",
                                  "TableName": "产品表",
                                  "ColumnName": "产品编号",
                                  "GUID": "f5fa0329-ad8f-434b-8ec2-cd52edd944ef"
                                },
                                "Value": {
                                  "$type": "Forguncy.Model.FormulaReferObject, ServerDesignerCommon",
                                  "SerializeProperty": "=产品编号"
                                }
                              },
                              {
                                "$type": "Forguncy.Model.UpdateBindingValueItem, ServerDesignerCommon",
                                "BindingInfo": {
                                  "$type": "ForguncyDataAccess.BindingInfo, ForguncyDataAccess",
                                  "TableName": "产品表",
                                  "ColumnName": "名称",
                                  "GUID": "a65f7a72-0f9b-4a64-97bb-d2cf29c6e3c9"
                                },
                                "Value": {
                                  "$type": "Forguncy.Model.FormulaReferObject, ServerDesignerCommon",
                                  "SerializeProperty": "=名称"
                                }
                              },
                              {
                                "$type": "Forguncy.Model.UpdateBindingValueItem, ServerDesignerCommon",
                                "BindingInfo": {
                                  "$type": "ForguncyDataAccess.BindingInfo, ForguncyDataAccess",
                                  "TableName": "产品表",
                                  "ColumnName": "类型",
                                  "GUID": "b46da078-b517-437a-ae8c-a755433e19d6"
                                },
                                "Value": {
                                  "$type": "Forguncy.Model.FormulaReferObject, ServerDesignerCommon",
                                  "SerializeProperty": "=类型"
                                }
                              },
                              {
                                "$type": "Forguncy.Model.UpdateBindingValueItem, ServerDesignerCommon",
                                "BindingInfo": {
                                  "$type": "ForguncyDataAccess.BindingInfo, ForguncyDataAccess",
                                  "TableName": "产品表",
                                  "ColumnName": "定价",
                                  "GUID": "133a68fe-0dda-48b7-b1a0-f1dade3f796c"
                                },
                                "Value": {
                                  "$type": "Forguncy.Model.FormulaReferObject, ServerDesignerCommon",
                                  "SerializeProperty": "=定价"
                                }
                              },
                              {
                                "$type": "Forguncy.Model.UpdateBindingValueItem, ServerDesignerCommon",
                                "BindingInfo": {
                                  "$type": "ForguncyDataAccess.BindingInfo, ForguncyDataAccess",
                                  "TableName": "产品表",
                                  "ColumnName": "备注",
                                  "GUID": "37577afd-72ae-4a2a-b9c6-7c13f3f2dcff"
                                },
                                "Value": {
                                  "$type": "Forguncy.Model.FormulaReferObject, ServerDesignerCommon",
                                  "SerializeProperty": "=备注"
                                }
                              }
                            ]
                          },
                          "BreakpointIdentity": "1a734b3e-c756-49f9-8c87-f8ef620ac3ff"
                        }
                      ]
                    },
                    "ID": "37a10b6a-e62d-4e30-b18c-b294ad4b3e89"
                  },
                  {
                    "$type": "Forguncy.Model.ConditionAndCommandPair, ServerDesignerCommon",
                    "CommandList": {
                      "$type": "System.Collections.Generic.List`1[[GrapeCity.Forguncy.Commands.Command, Forguncy.Commands]], System.Private.CoreLib",
                      "$values": [
                        {
                          "$type": "Forguncy.Model.UpdateDataTableCommand, ServerDesignerCommon",
                          "TableName": "产品表",
                          "UpdateType": "add",
                          "ShowConfirm": false,
                          "UpdateBindingValues": {
                            "$type": "System.Collections.Generic.List`1[[Forguncy.Model.UpdateBindingValueItem, ServerDesignerCommon]], System.Private.CoreLib",
                            "$values": [
                              {
                                "$type": "Forguncy.Model.UpdateBindingValueItem, ServerDesignerCommon",
                                "BindingInfo": {
                                  "$type": "ForguncyDataAccess.BindingInfo, ForguncyDataAccess",
                                  "TableName": "产品表",
                                  "ColumnName": "产品编号",
                                  "GUID": "f3712427-0208-4947-b1df-ed133d4eaf2e"
                                },
                                "Value": {
                                  "$type": "Forguncy.Model.FormulaReferObject, ServerDesignerCommon",
                                  "SerializeProperty": "=产品编号"
                                }
                              },
                              {
                                "$type": "Forguncy.Model.UpdateBindingValueItem, ServerDesignerCommon",
                                "BindingInfo": {
                                  "$type": "ForguncyDataAccess.BindingInfo, ForguncyDataAccess",
                                  "TableName": "产品表",
                                  "ColumnName": "名称",
                                  "GUID": "17bf88f9-2ace-426d-bb12-bfbc5f94019c"
                                },
                                "Value": {
                                  "$type": "Forguncy.Model.FormulaReferObject, ServerDesignerCommon",
                                  "SerializeProperty": "=名称"
                                }
                              },
                              {
                                "$type": "Forguncy.Model.UpdateBindingValueItem, ServerDesignerCommon",
                                "BindingInfo": {
                                  "$type": "ForguncyDataAccess.BindingInfo, ForguncyDataAccess",
                                  "TableName": "产品表",
                                  "ColumnName": "类型",
                                  "GUID": "88e410eb-d4b9-45cd-9541-13bcc1ba5a85"
                                },
                                "Value": {
                                  "$type": "Forguncy.Model.FormulaReferObject, ServerDesignerCommon",
                                  "SerializeProperty": "=类型"
                                }
                              },
                              {
                                "$type": "Forguncy.Model.UpdateBindingValueItem, ServerDesignerCommon",
                                "BindingInfo": {
                                  "$type": "ForguncyDataAccess.BindingInfo, ForguncyDataAccess",
                                  "TableName": "产品表",
                                  "ColumnName": "定价",
                                  "GUID": "43d07f13-d778-458c-a38c-3463a522b79d"
                                },
                                "Value": {
                                  "$type": "Forguncy.Model.FormulaReferObject, ServerDesignerCommon",
                                  "SerializeProperty": "=定价"
                                }
                              },
                              {
                                "$type": "Forguncy.Model.UpdateBindingValueItem, ServerDesignerCommon",
                                "BindingInfo": {
                                  "$type": "ForguncyDataAccess.BindingInfo, ForguncyDataAccess",
                                  "TableName": "产品表",
                                  "ColumnName": "备注",
                                  "GUID": "de223b3f-0a16-4a5c-bcad-b95bebcdd490"
                                },
                                "Value": {
                                  "$type": "Forguncy.Model.FormulaReferObject, ServerDesignerCommon",
                                  "SerializeProperty": "=备注"
                                }
                              }
                            ]
                          },
                          "BreakpointIdentity": "d1f6b689-91f5-4c78-b3d4-fbe4510480b7"
                        }
                      ]
                    },
                    "ID": "9d55a3da-f8d4-4f2b-878f-5383fedb5d8c"
                  }
                ]
              },
              "BreakpointIdentity": "09fb27fb-684a-46e5-9fc0-3f2386beed88"
            },
            {
              "$type": "Forguncy.Model.Commands.SetParameterCommand, ServerDesignerCommon",
              "ParameterName": "类型行数",
              "TableValue": {
                "$type": "Forguncy.Model.Commands.ParameterTableValue, ServerDesignerCommon",
                "TableName": "产品类型表",
                "TableValueType": 3,
                "SqlCondition": {
                  "$type": "ForguncyDataAccess.GeneralCESqlCondition, ForguncyDataAccess",
                  "ColumnBindingInfo": {
                    "$type": "ForguncyDataAccess.BindingInfo, ForguncyDataAccess",
                    "TableName": "产品类型表",
                    "ColumnName": "类型",
                    "GUID": "8adc9a59-95e6-445b-be5d-3b684fa1746a"
                  },
                  "Value": {
                    "$type": "Forguncy.Model.FormulaReferObject, ServerDesignerCommon",
                    "SerializeProperty": "=类型"
                  }
                }
              },
              "ID": "0a98653c4a944d7386a2e24139f71fe3",
              "BreakpointIdentity": "56a0f4e3-4406-46f7-845d-79215c93e747"
            },
            {
              "$type": "Forguncy.Model.ConditionCommand, ServerDesignerCommon",
              "ConditionAndCommandPairList": {
                "$type": "System.Collections.Generic.List`1[[Forguncy.Model.ConditionAndCommandPair, ServerDesignerCommon]], System.Private.CoreLib",
                "$values": [
                  {
                    "$type": "Forguncy.Model.ConditionAndCommandPair, ServerDesignerCommon",
                    "Condition": {
                      "$type": "Forguncy.Model.IfCondition, ServerDesignerCommon",
                      "param": {
                        "$type": "Forguncy.Model.IfConditionServerSiteParam, ServerDesignerCommon",
                        "ParamObject": {
                          "$type": "Forguncy.Model.FormulaReferObject, ServerDesignerCommon",
                          "SerializeProperty": "=类型行数"
                        }
                      },
                      "value": "0"
                    },
                    "CommandList": {
                      "$type": "System.Collections.Generic.List`1[[GrapeCity.Forguncy.Commands.Command, Forguncy.Commands]], System.Private.CoreLib",
                      "$values": [
                        {
                          "$type": "Forguncy.Model.UpdateDataTableCommand, ServerDesignerCommon",
                          "TableName": "产品类型表",
                          "UpdateType": "add",
                          "ShowConfirm": false,
                          "UpdateBindingValues": {
                            "$type": "System.Collections.Generic.List`1[[Forguncy.Model.UpdateBindingValueItem, ServerDesignerCommon]], System.Private.CoreLib",
                            "$values": [
                              {
                                "$type": "Forguncy.Model.UpdateBindingValueItem, ServerDesignerCommon",
                                "BindingInfo": {
                                  "$type": "ForguncyDataAccess.BindingInfo, ForguncyDataAccess",
                                  "TableName": "产品类型表",
                                  "ColumnName": "类型",
                                  "GUID": "8d47ef2f-91bf-4359-a6a4-758685c52342"
                                },
                                "Value": {
                                  "$type": "Forguncy.Model.FormulaReferObject, ServerDesignerCommon",
                                  "SerializeProperty": "=类型"
                                }
                              }
                            ]
                          },
                          "BreakpointIdentity": "b94cabab-55a1-4080-af72-433f0621f7ed"
                        }
                      ]
                    },
                    "ID": "6167c84f-7b37-4e5c-a85c-81e6f2dc4f0e"
                  }
                ]
              },
              "BreakpointIdentity": "e5d986cd-5fb4-4f3d-8ebb-72c18c1e3a7a"
            }
          ]
        },
        "BreakpointIdentity": "ea20b6e2-d3a7-4952-b821-80c412197b31"
      }
    ]
  }
}